retinawhitenoise-1.0.1.dist-info/WHEEL
retinawhitenoise-1.0.1.dist-info/LICENSE
retinawhitenoise-1.0.1.dist-info/RECORD
retinawhitenoise-1.0.1.dist-info/top_level.txt
retinawhitenoise-1.0.1.dist-info/METADATA
retinawhitenoise/gaussianstimulus.py
retinawhitenoise/_rng.cpython-311-i386-linux-musl.so
retinawhitenoise/_core.py
retinawhitenoise/__init__.py
retinawhitenoise/binarystimulus.py
