Metadata-Version: 2.1
Name: retinawhitenoise
Version: 1.0.1
Summary: Recreate white-noise stimuli
Author: Christian Mendl, Fernando Rozenblit, Sören Zapp
Maintainer: Gollisch Lab
License: MIT
Project-URL: Repository, https://github.com/gollischlab/RecreateWhiteNoiseStimuliWithPython.git
Keywords: retina,stimulus,white noise
Classifier: Intended Audience :: Science/Research
Classifier: Operating System :: OS Independent
Classifier: Topic :: Scientific/Engineering
Requires-Python: >=3.7
License-File: LICENSE
Requires-Dist: numpy>=1.16.0
Requires-Dist: h5py>=3.2
Requires-Dist: pathlib
Requires-Dist: tqdm
